{
  "_generated": "Generated by SweetTooth, do not edit", 
  "description": "Add dynamic quicklists to app icons, with Nautilus bookmarks and recent files.", 
  "gettext-domain": "quicklists",
  "settings-schema": "org.gnome.shell.extensions.quicklists",
  "name": "Quicklists", 
  "shell-version": [
    "3.18",
    "3.20",
    "3.22",
    "3.24",
    "3.26",
    "3.28",
    "3.30"
  ],
  "url": "https://github.com/maoschanz/quicklists-gnome-shell-extension", 
  "uuid": "quicklists@maestroschan.fr",
  "version": 2
}
